remarkabletools_mx_smartsend/__init__.py
remarkabletools_mx_smartsend/constants.py
remarkabletools_mx_smartsend/helper.py
remarkabletools_mx_smartsend/smart_send.py
remarkabletools_mx_smartsend/token_amount.py
remarkabletools_mx_smartsend-1.0.0.dist-info/METADATA
remarkabletools_mx_smartsend-1.0.0.dist-info/WHEEL
remarkabletools_mx_smartsend-1.0.0.dist-info/licenses/LICENSE
remarkabletools_mx_smartsend-1.0.0.dist-info/RECORD
