Metadata-Version: 2.1
Name: remarkabletools-mx-smartsend
Version: 1.0.0
Summary: ⚡ MultiversX SmartSend Python SDK: Library for interacting with Smart Send contracts on MultiversX blockchain
Project-URL: Homepage, https://github.com/RemarkableTools/Mx.PY.SDK.SmartSend
Project-URL: Bug Tracker, https://github.com/RemarkableTools/Mx.PY.SDK.SmartSend/issues
Author: Remarkable Tools
License-Expression: MIT
License-File: LICENSE
Classifier: License :: OSI Approved :: MIT License
Classifier: Operating System :: OS Independent
Classifier: Programming Language :: Python :: 3
Requires-Python: >=3.8
